brython_pack/__init__.py
brython_pack/_version.py
brython_pack/main.py
brython_pack/pack.py
brython_pack/stdlib.py
brython_pack/utils.py
brython_pack-0.0.3.dist-info/DESCRIPTION.rst
brython_pack-0.0.3.dist-info/METADATA
brython_pack-0.0.3.dist-info/RECORD
brython_pack-0.0.3.dist-info/WHEEL
brython_pack-0.0.3.dist-info/entry_points.txt
brython_pack-0.0.3.dist-info/metadata.json
brython_pack-0.0.3.dist-info/top_level.txt
